LICENCE
README.md
setup.cfg
setup.py
bin/pymica_create_clusters_file
bin/pymica_distance_to_sea_calculator
bin/pymica_generate_clusters
cluster/__init__.py
cluster/create_cluster_files.py
cluster/create_clusters.py
distance/__init__.py
distance/distance_to_sea.py
interpolation/__init__.py
interpolation/idw.py
interpolation/inverse_distance.c
interpolation/inverse_distance_3d.c
pymica/__init__.py
pymica/apply_regression.py
pymica/clustered_regression.py
pymica/multiregression.py
pymica/pymica.py
pymica.egg-info/PKG-INFO
pymica.egg-info/SOURCES.txt
pymica.egg-info/dependency_links.txt
pymica.egg-info/requires.txt
pymica.egg-info/top_level.txt