Metadata-Version: 2.1
Name: pymica
Version: 0.0.33
Summary: pyMICA, Meteorological variable Interpolation basedon Clustered Analysis
Home-page: https://github.com/meteocat/pymica
License: UNKNOWN
Platform: UNKNOWN
Classifier: Development Status :: 2 - Pre-Alpha
Classifier: Intended Audience :: Science/Research
Classifier: Topic :: Scientific/Engineering
Classifier: Topic :: Scientific/Engineering :: Atmospheric Science
Classifier: License :: OSI Approved :: MIT License
Classifier: Programming Language :: Python :: 3
Classifier: Programming Language :: Python :: 3.9
License-File: LICENCE
